moosefs_tricorder/__init__.py
moosefs_tricorder/cli.py
moosefs_tricorder/common.py
moosefs_tricorder/moosefs.py
moosefs_tricorder-0.1.0.dist-info/LICENSE
moosefs_tricorder-0.1.0.dist-info/METADATA
moosefs_tricorder-0.1.0.dist-info/WHEEL
moosefs_tricorder-0.1.0.dist-info/entry_points.txt
moosefs_tricorder-0.1.0.dist-info/RECORD
