Metadata-Version: 2.1
Name: moosefs-tricorder
Version: 0.1.0
Summary: 
Author: Joe Block
Author-email: jpb@unixorn.net
Requires-Python: >=3.9,<4.0
Classifier: Programming Language :: Python :: 3
Classifier: Programming Language :: Python :: 3.9
Classifier: Programming Language :: Python :: 3.10
Classifier: Programming Language :: Python :: 3.11
Requires-Dist: prometheus-client (>=0.17.1,<0.18.0)
